README.md
setup.py
keywordtree/__init__.py
keywordtree/keywordtree.py
keywordtree.egg-info/PKG-INFO
keywordtree.egg-info/SOURCES.txt
keywordtree.egg-info/dependency_links.txt
keywordtree.egg-info/top_level.txt
test/test_simple.py