Metadata-Version: 2.1
Name: keywordtree
Version: 0.1.6
Summary: UNKNOWN
Home-page: https://github.com/tdiam/keywordtree
Author: Theodoros Diamantidis
Author-email: diamaltho@gmail.com
License: MIT
Platform: UNKNOWN
Classifier: Development Status :: 1 - Planning
Classifier: License :: OSI Approved :: MIT License
Classifier: Operating System :: OS Independent
Classifier: Programming Language :: Python
Classifier: Programming Language :: Python :: 3 :: Only
Classifier: Topic :: Software Development :: Libraries :: Python Modules
Classifier: Topic :: Text Processing
Classifier: Topic :: Text Processing :: General
Requires-Python: >=3
